x_dm_python/__init__.py
x_dm_python/dm/__init__.py
x_dm_python/fingerprint/__init__.py
x_dm_python/inbox/__init__.py
x_dm_python/posts/__init__.py
x_dm_python/upload/__init__.py
x_dm_python/user/__init__.py
x_dm_python/x_dm_python.abi3.so
x_dm_python/x_dm_python.pyi
x_dm_python-1.1.9.dist-info/METADATA
x_dm_python-1.1.9.dist-info/WHEEL
x_dm_python-1.1.9.dist-info/RECORD
