Metadata-Version: 2.4
Name: x_dm_python
Version: 1.1.9
Classifier: Programming Language :: Rust
Classifier: Programming Language :: Python :: 3
Classifier: Programming Language :: Python :: 3.8
Classifier: Programming Language :: Python :: 3.9
Classifier: Programming Language :: Python :: 3.10
Classifier: Programming Language :: Python :: 3.11
Classifier: Programming Language :: Python :: 3.12
Classifier: Programming Language :: Python :: 3.13
Classifier: License :: OSI Approved :: MIT License
Classifier: Operating System :: OS Independent
Requires-Dist: pytest>=7.0 ; extra == 'test'
Requires-Dist: pytest-asyncio>=0.21 ; extra == 'test'
Provides-Extra: test
Summary: Twitter DM 批量并发发送库 (Rust 实现, 提供 Python 绑定)
Author-email: robin <robin528919@gmail.com>
Requires-Python: >=3.8
Project-URL: Homepage, https://github.com/yourusername/twitter-dm-static
Project-URL: Issues, https://github.com/yourusername/twitter-dm-static/issues
Project-URL: Repository, https://github.com/yourusername/twitter-dm-static.git
